extrange/__init__.py
extrange/range.py
extrange/test_range.py
extrange/test_timerange.py
extrange/timerange.py
extrange-1.0.0.dist-info/LICENSE
extrange-1.0.0.dist-info/METADATA
extrange-1.0.0.dist-info/WHEEL
extrange-1.0.0.dist-info/top_level.txt
extrange-1.0.0.dist-info/RECORD
